{
  "ward": "Dana Ranch Ward",
  "isFastSunday": false,
  "broadcastLink": "https://www.youtube.com/watch?v=4OQTBfmoMg8",
  "secureHash": "1",
  "image": "https://cdn.shopify.com/s/files/1/0241/8678/1751/files/New_Homepage_Banner_-_Desktop.jpg?v=1668559606",
  "organist": "Whitney Kolstad",
  "chorister": "Cindy Fast",
  "presiding": "Bishop Kent",
  "conducting": "Bishop Kent",
  "invocation": {
    "type": "Invocation",
    "name": "Ashlee Gray"
  },
  "benediction": {
    "type": "Benediction",
    "name": "Paden Gray"
  },
  "openingHymn": {
    "type": "Opening Hymn",
    "title": "God of our Fathers",
    "number": 78,
    "link": null
  },
  "sacramentHymn": {
    "type": "Sacrament Hymn",
    "title": "There is a Green Hill Far Away",
    "number": 194,
    "link": null
  },
  "closingHymn": {
    "type": "Closing Hymn",
    "title": "Abide with Me Tis Eventide",
    "number": 165,
    "link": null
  },
  "services": [
    {
      "type": "Speaker",
      "name": "Juliet Coleman"
    },
    {
      "type": "Speaker",
      "name": "Kinsey Wallace"
    },
    {
      "type": "Congregational Hymn",
      "musicians": [
        "60"
      ],
      "title": "Battle Hymn"
    },
    {
      "type": "Speaker",
      "name": "Nicholas Wallace"
    }
  ],
  "announcements": [],
  "wardBusiness": {
    "baptisms": [],
    "ordinations": [],
    "newMoveIns": [
      "Nielson Family: Camden, Olivia, and Cosette"
    ],
    "other": [],
    "releases": [
    ],
    "callings": [
      "Ben and Melissa Murray as Primary Teachers"
    ],
    "deaths": []
  }
}